Workbook

Sheet Assumptions
B1: IMAX Corporation (NYSE: IMAX) - Valuation Assumptions
B2: Blue = input / lever. Black = calculated. All figures US$mm unless noted.
B4: VALUATION INPUTS | D4: Source / note
B5: Cost of equity | C5: =C105 -> 0.1069 | D5: Now built from CAPM below (Rf + beta x ERP), not hard-coded. ~94% equity weighting means WACC approximates cost of equity.
B6: Terminal growth rate | C6: 0.0275 | D6: Perpetuity growth. Below long-run nominal GDP. 2035 treated as mid-cycle, not peak.
B7: Diluted shares outstanding (mm) | C7: 56.6 | D7: Q2 2026 10-Q. 54.84mm basic + dilution. No buybacks modelled - see note below.
B8: Non-controlling interest ($mm) | C8: 100 | D8: IMAX China (HK:1970) 28.43% minority. Book $93.8mm at Jun-30-26; deducted at ~$100mm to approximate HK market value (~$95-110mm). Refresh to latest quote before publishing.
B9: Current share price | C9: 44 | D9: Post-Q2 print, 23-Jul-2026. Stock rose ~14% on the day; 52-wk high $43.96. Prior $37.85 was pre-print (21-Jul).
B10: Consensus price target | C10: 47 | D10: Street range $41-50: Seaport $50, Roth $48, Rosenblatt $47, Goldman $42, Wells Fargo $41 (downgraded to Equal Weight 16-Jul on valuation).
B12: HISTORICAL ANCHORS | D12: Source
B13: FY2025 revenue | C13: 410.2 | D13: FY2025 10-K, Note 20 Segment Reporting.
B14: FY2025 Adj. EBITDA | C14: 185 | D14: 45.1% margin per FY2025 investor presentation.
B15: FY2025 free cash flow | C15: 85.2 | D15: OCF $127.1mm less PP&E $8.2mm, JRSA investment $28.4mm, intangibles $5.3mm.
B16: FY2025 FCF conversion | C16: 0.46 | D16: $85.2mm / $185.0mm. The starting point for the assumed conversion ramp.
B17: FY2025 IMAX global box office ($bn) | C17: 1.28 | D17: FY2025 results. 2024: $0.92bn.
B18: Commercial multiplex systems, Jun-2026 | C18: 1809 | D18: Q2 2026 10-Q, IMAX Network and Backlog.
B19: FY2025 box office capture rate | C19: 0.182 | D19: ($142.3mm remastering + $82.2mm rentals) / $1.28bn. Studios pay ~11-12.5%; JRSA exhibitors pay ~12.5% more.
B21: KEY MODELLING DECISIONS (analyst estimates)
B22: Network target 2035 | C22: 2,500 systems | D22: Analyst estimate. ~70 net adds/yr; ~170 gross installs at ~100 closures/yr = in line with 160-175 guidance sustained.
B23: Cyclicality | C23: 2 down years | D23: Analyst estimate. 2027 (-9% vs 2026 Odyssey/Dune peak) and 2032 (-4% vs 2031 local peak). Trend upward.
B24: Buybacks | C24: Not modelled | D24: Buybacks are value-neutral at fair value. Model DCF ~$29-42/sh vs $37.85 price implies repurchases may DESTROY value. Discuss, do not model.
B25: Box office capture | C25: 18.5%, -15bp/yr | D25: Analyst estimate. Decay reflects network mix shifting to sales arrangements (no JRSA rent); partly offset by falling China weight.
B26: The Odyssey (2026) | C26: $1.2bn WW / 25% IMAX | D26: Analyst estimate. 5.25x on $264.1mm opening (Oppenheimer 5.42x). 25% capture is above prior precedent (Oppenheimer ~19.5%), supported by IMAX pricing power on a Filmed-for-IMAX title.
B27: Dune: Part Three (2026) | C27: $450mm in-year | D27: Analyst estimate. Bull case; ~$100mm IMAX. Opens 18-Dec-26 with IMAX-exclusive opening weekend.
B28: FCF conversion path | C28: 50% -> 55% by 2030 | D28: Analyst estimate. Above the 46% realized in FY2025; rests on operating leverage on higher box office, with JRSA and lease-incentive spend still rising.
B30: STRUCTURAL NOTES
B31: Equity FCF, not unlevered | D31: IMAX FCF = operating cash flow less capex. OCF is already post-interest and post-tax, so this is an EQUITY cash flow. Discount at cost of equity; do NOT deduct net debt.
B32: No separate receivables add-back | D32: Balance sheet carries $330mm of receivables (36% of assets) representing already-recognised revenue. Collections appear in operating cash flow. Adding them again double-counts.
B33: NCI deducted at market | D33: IMAX consolidates 100% of IMAX China but owns 71.57%. Deducted from equity value, not from cash flows.
B34: Revenue != cash | D34: Sales arrangements book PV of future minimums AND estimated contingent box-office fees at installation. $97.5mm variable consideration receivable is revenue booked on a forecast of exhibitors' future box office.
B95: TERMINAL STRUCTURE (blended, per Howmet template)
B96: Exit multiple (EV/EBITDA on 2035E) | C96: 12.5 | D96: Below the 14.5x comps multiple to reflect terminal-year maturity. Blue input.
B97: Weight - exit multiple | C97: 0.65 | D97: Mirrors the Howmet reference (65% exit / 35% perpetuity).
B98: Weight - perpetuity growth | C98: 0.35 | D98: Perpetuity uses the terminal growth rate above (2.75%).
B99: Terminal net debt assumption ($mm) | C99: 132 | D99: Assumes excess cash returned to holders, so terminal net debt approximates current. Simplification.
B101: COST OF EQUITY BUILD (CAPM) | D101: Source / note
B102: Risk-free rate (US 10-yr Treasury) | C102: 0.0471 | D102: Market yield, 10-yr constant maturity, as at report date.
B103: Beta | C103: 1.3 | D103: Reflects asset-light licensing model dampening volatility vs a pure exhibitor. Low end of 1.3-1.5 range.
B104: Equity risk premium | C104: 0.046 | D104: Market-wide assumption; within the 4.5-5.5% range.
B105: Cost of equity (calculated) | C105: =C102+C103*C104 -> 0.1069 | D105: Rf + beta x ERP. Feeds the DCF discount rate.

Sheet Model
B1: IMAX Corporation - 10-Year Operating Model
B2: Blue = input / lever. Black = formula. US$mm unless noted.
B4: Year | C4: 2026E | D4: 2027E | E4: 2028E | F4: 2029E | G4: 2030E | H4: 2031E | I4: 2032E | J4: 2033E | K4: 2034E | L4: 2035E
B5: Discount period | C5: 1 | D5: 2 | E5: 3 | F5: 4 | G5: 5 | H5: 6 | I5: 7 | J5: 8 | K5: 9 | L5: 10
B7: NETWORK
B8: Systems, beginning of year | C8: 1796 | D8: =C10 -> 1870 | E8: =D10 -> 1935 | F8: =E10 -> 2003 | G8: =F10 -> 2072 | H8: =G10 -> 2143 | I8: =H10 -> 2215 | J8: =I10 -> 2286 | K8: =J10 -> 2358 | L8: =K10 -> 2429
B9: Net additions | C9: 74 | D9: 65 | E9: 68 | F9: 69 | G9: 71 | H9: 72 | I9: 71 | J9: 72 | K9: 71 | L9: 71
B10: Systems, end of year | C10: =C8+C9 -> 1870 | D10: =D8+D9 -> 1935 | E10: =E8+E9 -> 2003 | F10: =F8+F9 -> 2072 | G10: =G8+G9 -> 2143 | H10: =H8+H9 -> 2215 | I10: =I8+I9 -> 2286 | J10: =J8+J9 -> 2358 | ... L10: =L8+L9 -> 2500
B11: Average systems | C11: =(C8+C10)/2 -> 1833 | D11: =(D8+D10)/2 -> 1902.5 | E11: =(E8+E10)/2 -> 1969 | F11: =(F8+F10)/2 -> 2037.5 | G11: =(G8+G10)/2 -> 2107.5 | H11: =(H8+H10)/2 -> 2179 | I11: =(I8+I10)/2 -> 2250.5 | J11: =(J8+J10)/2 -> 2322 | ... L11: =(L8+L10)/2 -> 2464.5
B13: BOX OFFICE
B14: Box office per screen ($000) | C14: 889 | D14: 780 | E14: 800 | F14: 815 | G14: 830 | H14: 845 | I14: 785 | J14: 850 | K14: 865 | L14: 880
B15: Global IMAX box office ($mm) | C15: =C11*C14/1000 -> 1629.537 | D15: =D11*D14/1000 -> 1483.95 | E15: =E11*E14/1000 -> 1575.2 | F15: =F11*F14/1000 -> 1660.5625 | G15: =G11*G14/1000 -> 1749.225 | H15: =H11*H14/1000 -> 1841.255 | I15: =I11*I14/1000 -> 1766.6425 | J15: =J11*J14/1000 -> 1973.7 | ... L15: =L11*L14/1000 -> 2168.76
B16: y/y growth | D16: =D15/C15-1 -> -0.089342556 | E16: =E15/D15-1 -> 0.06149129 | F16: =F15/E15-1 -> 0.054191531 | G16: =G15/F15-1 -> 0.053393052 | H16: =H15/G15-1 -> 0.052611871 | I16: =I15/H15-1 -> -0.040522633 | J16: =J15/I15-1 -> 0.11720396 | K16: =K15/J15-1 -> 0.048982875 | L16: =L15/K15-1 -> 0.047519112
B18: REVENUE
B19: Box office capture rate | C19: 0.185 | D19: 0.1835 | E19: 0.182 | F19: 0.1805 | G19: 0.179 | H19: 0.1775 | I19: 0.176 | J19: 0.1745 | K19: 0.173 | L19: 0.1715
B20: Box-office-linked revenue | C20: =C15*C19 -> 301.46434 | D20: =D15*D19 -> 272.30482 | E20: =E15*E19 -> 286.6864 | F20: =F15*F19 -> 299.73153 | G20: =G15*G19 -> 313.11127 | H20: =H15*H19 -> 326.82276 | I20: =I15*I19 -> 310.92908 | J20: =J15*J19 -> 344.41065 | ... L20: =L15*L19 -> 371.94234
B21: System sales | C21: 113 | D21: 115 | E21: 118 | F21: 120 | G21: 122 | H21: 125 | I21: 127 | J21: 130 | K21: 132 | L21: 135
B22: Maintenance | C22: 70 | D22: 74 | E22: 77 | F22: 81 | G22: 85 | H22: 90 | I22: 94 | J22: 99 | K22: 104 | L22: 109
B23: Finance income | C23: 12 | D23: 12.5 | E23: 13 | F23: 13.5 | G23: 14 | H23: 14.6 | I23: 15.2 | J23: 15.8 | K23: 16.4 | L23: 17.1
B24: All other | C24: 12 | D24: 12.6 | E24: 13.2 | F24: 13.9 | G24: 14.6 | H24: 15.3 | I24: 16.1 | J24: 16.9 | K24: 17.7 | L24: 18.6
B25: Total non-box-office revenue | C25: =SUM(C21:C24) -> 207 | D25: =SUM(D21:D24) -> 214.1 | E25: =SUM(E21:E24) -> 221.2 | F25: =SUM(F21:F24) -> 228.4 | G25: =SUM(G21:G24) -> 235.6 | H25: =SUM(H21:H24) -> 244.9 | I25: =SUM(I21:I24) -> 252.3 | J25: =SUM(J21:J24) -> 261.7 | ... L25: =SUM(L21:L24) -> 279.7
B26: Total revenue | C26: =C20+C25 -> 508.46434 | D26: =D20+D25 -> 486.40482 | E26: =E20+E25 -> 507.8864 | F26: =F20+F25 -> 528.13153 | G26: =G20+G25 -> 548.71128 | H26: =H20+H25 -> 571.72276 | I26: =I20+I25 -> 563.22908 | J26: =J20+J25 -> 606.11065 | ... L26: =L20+L25 -> 651.64234
B27: y/y growth | C27: =C26/Assumptions!$C$13-1 -> 0.23955228 | D27: =D26/C26-1 -> -0.043384596 | E27: =E26/D26-1 -> 0.044163984 | F27: =F26/E26-1 -> 0.039861534 | G27: =G26/F26-1 -> 0.03896708 | H27: =H26/G26-1 -> 0.041937333 | I27: =I26/H26-1 -> -0.014856296 | J27: =J26/I26-1 -> 0.07613522 | K27: =K26/J26-1 -> 0.036568665 | L27: =L26/K26-1 -> 0.037192346
B29: PROFITABILITY
B30: Adj. EBITDA margin | C30: 0.46 | D30: 0.455 | E30: 0.48 | F30: 0.49 | G30: 0.5 | H30: 0.5 | I30: 0.485 | J30: 0.5 | K30: 0.5 | L30: 0.5
B31: Adj. EBITDA | C31: =C26*C30 -> 233.8936 | D31: =D26*D30 -> 221.3142 | E31: =E26*E30 -> 243.78547 | F31: =F26*F30 -> 258.78445 | G31: =G26*G30 -> 274.35564 | H31: =H26*H30 -> 285.86138 | I31: =I26*I30 -> 273.1661 | J31: =J26*J30 -> 303.05532 | ... L31: =L26*L30 -> 325.82117
B33: FREE CASH FLOW
B34: FCF conversion (% of Adj. EBITDA) | C34: 0.5 | D34: 0.51 | E34: 0.52 | F34: 0.535 | G34: 0.55 | H34: 0.55 | I34: 0.55 | J34: 0.55 | K34: 0.55 | L34: 0.55
B35: Free cash flow (equity) | C35: =C31*C34 -> 116.9468 | D35: =D31*D34 -> 112.87024 | E35: =E31*E34 -> 126.76845 | F35: =F31*F34 -> 138.44968 | G35: =G31*G34 -> 150.8956 | H35: =H31*H34 -> 157.22376 | I35: =I31*I34 -> 150.24136 | J35: =J31*J34 -> 166.68043 | ... L35: =L31*L34 -> 179.20164
B36: as % of revenue | C36: =C35/C26 -> 0.23 | D36: =D35/D26 -> 0.23205 | E36: =E35/E26 -> 0.2496 | F36: =F35/F26 -> 0.26215 | G36: =G35/G26 -> 0.275 | H36: =H35/H26 -> 0.275 | I36: =I35/I26 -> 0.26675 | J36: =J35/J26 -> 0.275 | ... L36: =L35/L26 -> 0.275
B38: Down years: 2027 (-9% vs 2026 Odyssey/Dune peak) and 2032 (-4% vs 2031). Trend upward throughout.
B39: Per-screen box office and margins are the primary levers. Both are blue inputs - overwrite to test.

Sheet DCF
B1: IMAX Corporation - Discounted Cash Flow
B2: Equity FCF discounted at cost of equity; net debt NOT deducted from the FCF stream (OCF is already post-interest). Net debt IS subtracted only on the exit-multiple terminal line, to convert that EV-based figure to equity.
B4: Year | C4: 2026E | D4: 2027E | E4: 2028E | F4: 2029E | G4: 2030E | H4: 2031E | I4: 2032E | J4: 2033E | K4: 2034E | L4: 2035E
B5: Discount period | C5: =Model!C5 -> 1 | D5: =Model!D5 -> 2 | E5: =Model!E5 -> 3 | F5: =Model!F5 -> 4 | G5: =Model!G5 -> 5 | H5: =Model!H5 -> 6 | I5: =Model!I5 -> 7 | J5: =Model!J5 -> 8 | ... L5: =Model!L5 -> 10
B6: Free cash flow (equity) | C6: =Model!C35 -> 116.9468 | D6: =Model!D35 -> 112.87024 | E6: =Model!E35 -> 126.76845 | F6: =Model!F35 -> 138.44968 | G6: =Model!G35 -> 150.8956 | H6: =Model!H35 -> 157.22376 | I6: =Model!I35 -> 150.24136 | J6: =Model!J35 -> 166.68043 | ... L6: =Model!L35 -> 179.20164
B7: Discount factor | C7: =1/(1+Assumptions!$C$5)^C5 -> 0.90342398 | D7: =1/(1+Assumptions!$C$5)^D5 -> 0.81617488 | E7: =1/(1+Assumptions!$C$5)^E5 -> 0.73735196 | F7: =1/(1+Assumptions!$C$5)^F5 -> 0.66614144 | G7: =1/(1+Assumptions!$C$5)^G5 -> 0.60180815 | H7: =1/(1+Assumptions!$C$5)^H5 -> 0.54368791 | I7: =1/(1+Assumptions!$C$5)^I5 -> 0.49118069 | J7: =1/(1+Assumptions!$C$5)^J5 -> 0.44374442 | ... L7: =1/(1+Assumptions!$C$5)^L5 -> 0.36217305
B8: PV of free cash flow | C8: =C6*C7 -> 105.65254 | D8: =D6*D7 -> 92.121855 | E8: =E6*E7 -> 93.472961 | F8: =F6*F7 -> 92.22707 | G8: =G6*G7 -> 90.810202 | H8: =H6*H7 -> 85.480657 | I8: =I6*I7 -> 73.795654 | J8: =J6*J7 -> 73.963509 | ... L8: =L6*L7 -> 64.902005
B10: VALUATION
B11: PV of explicit forecast (2026-2035) | C11: =SUM(C8:L8) -> 841.6904
B12: Terminal EBITDA (2035E) | C12: =Model!L31 -> 325.82117
B13: Terminal value - exit multiple (equity) | C13: =Assumptions!C96*Model!L31-Assumptions!C99 -> 3940.7646
B14: Terminal value - perpetuity (equity) | C14: =L6*(1+Assumptions!$C$6)/(Assumptions!$C$5-Assumptions!$C$6) -> 2319.0137
B15: Blended terminal value | C15: =Assumptions!C97*C13+Assumptions!C98*C14 -> 3373.1518
B16: PV of blended terminal value | C16: =C15*L7 -> 1221.6647
B17: Total equity value (consolidated) | C17: =C11+C16 -> 2063.3551
B18: Less: non-controlling interest | C18: =-Assumptions!$C$8 -> -100
B19: Equity value to IMAX shareholders | C19: =C17+C18 -> 1963.3551
B20: Diluted shares (mm) | C20: =Assumptions!$C$7 -> 56.6
B21: Value per share | C21: =C19/C20 -> 34.688252
B23: CROSS-CHECK
B24: Current share price | C24: =Assumptions!$C$9 -> 44 | D24: Blended terminal = 65% exit multiple + 35% perpetuity, per Howmet template.
B25: Upside / (downside) to DCF | C25: =C21/C24-1 -> -0.21163064
B26: Consensus price target | C26: =Assumptions!$C$10 -> 47
B27: DCF vs consensus | C27: =C21/C26-1 -> -0.26195209
B28: Blended terminal as % of total | C28: =C16/C17 -> 0.5920768
B29: Implied blended exit multiple | C29: =(C15)/Model!L31 -> 10.352771
B30: SENSITIVITY - DCF VALUE / SHARE (blended terminal)
B31: Cost of equity \ Exit multiple | C31: =Assumptions!$C$96+(-2) -> 10.5 | D31: =Assumptions!$C$96+(-1) -> 11.5 | E31: =Assumptions!$C$96+(0) -> 12.5 | F31: =Assumptions!$C$96+(1) -> 13.5 | G31: =Assumptions!$C$96+(2) -> 14.5
B32: =Assumptions!$C$5+(-0.01) -> 0.0969 | C32: =(SUMPRODUCT($C$6:$L$6,1/(1+$B32)^$C$5:$L$5)+(Assumptions!$C$97*(C$31*Model!$L$31-Assumptions!$C$99)+Assumptions!$C$98*($L$6*(1+Assumptions!$C$6)/($B32-Assumptions!$C$6)))/(1+$B32)^$L$5-Assumptions!$C$8)/Assumptions!$C$7 -> 35.299006 | D32: =(SUMPRODUCT($C$6:$L$6,1/(1+$B32)^$C$5:$L$5)+(Assumptions!$C$97*(D$31*Model!$L$31-Assumptions!$C$99)+Assumptions!$C$98*($L$6*(1+Assumptions!$C$6)/($B32-Assumptions!$C$6)))/(1+$B32)^$L$5-Assumptions!$C$8)/Assumptions!$C$7 -> 36.78291 | E32: =(SUMPRODUCT($C$6:$L$6,1/(1+$B32)^$C$5:$L$5)+(Assumptions!$C$97*(E$31*Model!$L$31-Assumptions!$C$99)+Assumptions!$C$98*($L$6*(1+Assumptions!$C$6)/($B32-Assumptions!$C$6)))/(1+$B32)^$L$5-Assumptions!$C$8)/Assumptions!$C$7 -> 38.266814 | F32: =(SUMPRODUCT($C$6:$L$6,1/(1+$B32)^$C$5:$L$5)+(Assumptions!$C$97*(F$31*Model!$L$31-Assumptions!$C$99)+Assumptions!$C$98*($L$6*(1+Assumptions!$C$6)/($B32-Assumptions!$C$6)))/(1+$B32)^$L$5-Assumptions!$C$8)/Assumptions!$C$7 -> 39.750718 | G32: =(SUMPRODUCT($C$6:$L$6,1/(1+$B32)^$C$5:$L$5)+(Assumptions!$C$97*(G$31*Model!$L$31-Assumptions!$C$99)+Assumptions!$C$98*($L$6*(1+Assumptions!$C$6)/($B32-Assumptions!$C$6)))/(1+$B32)^$L$5-Assumptions!$C$8)/Assumptions!$C$7 -> 41.234622
B33: =Assumptions!$C$5+(-0.005) -> 0.1019 | C33: =(SUMPRODUCT($C$6:$L$6,1/(1+$B33)^$C$5:$L$5)+(Assumptions!$C$97*(C$31*Model!$L$31-Assumptions!$C$99)+Assumptions!$C$98*($L$6*(1+Assumptions!$C$6)/($B33-Assumptions!$C$6)))/(1+$B33)^$L$5-Assumptions!$C$8)/Assumptions!$C$7 -> 33.565378 | D33: =(SUMPRODUCT($C$6:$L$6,1/(1+$B33)^$C$5:$L$5)+(Assumptions!$C$97*(D$31*Model!$L$31-Assumptions!$C$99)+Assumptions!$C$98*($L$6*(1+Assumptions!$C$6)/($B33-Assumptions!$C$6)))/(1+$B33)^$L$5-Assumptions!$C$8)/Assumptions!$C$7 -> 34.983307 | E33: =(SUMPRODUCT($C$6:$L$6,1/(1+$B33)^$C$5:$L$5)+(Assumptions!$C$97*(E$31*Model!$L$31-Assumptions!$C$99)+Assumptions!$C$98*($L$6*(1+Assumptions!$C$6)/($B33-Assumptions!$C$6)))/(1+$B33)^$L$5-Assumptions!$C$8)/Assumptions!$C$7 -> 36.401236 | F33: =(SUMPRODUCT($C$6:$L$6,1/(1+$B33)^$C$5:$L$5)+(Assumptions!$C$97*(F$31*Model!$L$31-Assumptions!$C$99)+Assumptions!$C$98*($L$6*(1+Assumptions!$C$6)/($B33-Assumptions!$C$6)))/(1+$B33)^$L$5-Assumptions!$C$8)/Assumptions!$C$7 -> 37.819164 | G33: =(SUMPRODUCT($C$6:$L$6,1/(1+$B33)^$C$5:$L$5)+(Assumptions!$C$97*(G$31*Model!$L$31-Assumptions!$C$99)+Assumptions!$C$98*($L$6*(1+Assumptions!$C$6)/($B33-Assumptions!$C$6)))/(1+$B33)^$L$5-Assumptions!$C$8)/Assumptions!$C$7 -> 39.237093
B34: =Assumptions!$C$5+(0) -> 0.1069 | C34: =(SUMPRODUCT($C$6:$L$6,1/(1+$B34)^$C$5:$L$5)+(Assumptions!$C$97*(C$31*Model!$L$31-Assumptions!$C$99)+Assumptions!$C$98*($L$6*(1+Assumptions!$C$6)/($B34-Assumptions!$C$6)))/(1+$B34)^$L$5-Assumptions!$C$8)/Assumptions!$C$7 -> 31.977921 | D34: =(SUMPRODUCT($C$6:$L$6,1/(1+$B34)^$C$5:$L$5)+(Assumptions!$C$97*(D$31*Model!$L$31-Assumptions!$C$99)+Assumptions!$C$98*($L$6*(1+Assumptions!$C$6)/($B34-Assumptions!$C$6)))/(1+$B34)^$L$5-Assumptions!$C$8)/Assumptions!$C$7 -> 33.333086 | E34: =(SUMPRODUCT($C$6:$L$6,1/(1+$B34)^$C$5:$L$5)+(Assumptions!$C$97*(E$31*Model!$L$31-Assumptions!$C$99)+Assumptions!$C$98*($L$6*(1+Assumptions!$C$6)/($B34-Assumptions!$C$6)))/(1+$B34)^$L$5-Assumptions!$C$8)/Assumptions!$C$7 -> 34.688252 | F34: =(SUMPRODUCT($C$6:$L$6,1/(1+$B34)^$C$5:$L$5)+(Assumptions!$C$97*(F$31*Model!$L$31-Assumptions!$C$99)+Assumptions!$C$98*($L$6*(1+Assumptions!$C$6)/($B34-Assumptions!$C$6)))/(1+$B34)^$L$5-Assumptions!$C$8)/Assumptions!$C$7 -> 36.043417 | G34: =(SUMPRODUCT($C$6:$L$6,1/(1+$B34)^$C$5:$L$5)+(Assumptions!$C$97*(G$31*Model!$L$31-Assumptions!$C$99)+Assumptions!$C$98*($L$6*(1+Assumptions!$C$6)/($B34-Assumptions!$C$6)))/(1+$B34)^$L$5-Assumptions!$C$8)/Assumptions!$C$7 -> 37.398583
B35: =Assumptions!$C$5+(0.005) -> 0.1119 | C35: =(SUMPRODUCT($C$6:$L$6,1/(1+$B35)^$C$5:$L$5)+(Assumptions!$C$97*(C$31*Model!$L$31-Assumptions!$C$99)+Assumptions!$C$98*($L$6*(1+Assumptions!$C$6)/($B35-Assumptions!$C$6)))/(1+$B35)^$L$5-Assumptions!$C$8)/Assumptions!$C$7 -> 30.51577 | D35: =(SUMPRODUCT($C$6:$L$6,1/(1+$B35)^$C$5:$L$5)+(Assumptions!$C$97*(D$31*Model!$L$31-Assumptions!$C$99)+Assumptions!$C$98*($L$6*(1+Assumptions!$C$6)/($B35-Assumptions!$C$6)))/(1+$B35)^$L$5-Assumptions!$C$8)/Assumptions!$C$7 -> 31.811214 | E35: =(SUMPRODUCT($C$6:$L$6,1/(1+$B35)^$C$5:$L$5)+(Assumptions!$C$97*(E$31*Model!$L$31-Assumptions!$C$99)+Assumptions!$C$98*($L$6*(1+Assumptions!$C$6)/($B35-Assumptions!$C$6)))/(1+$B35)^$L$5-Assumptions!$C$8)/Assumptions!$C$7 -> 33.106659 | F35: =(SUMPRODUCT($C$6:$L$6,1/(1+$B35)^$C$5:$L$5)+(Assumptions!$C$97*(F$31*Model!$L$31-Assumptions!$C$99)+Assumptions!$C$98*($L$6*(1+Assumptions!$C$6)/($B35-Assumptions!$C$6)))/(1+$B35)^$L$5-Assumptions!$C$8)/Assumptions!$C$7 -> 34.402104 | G35: =(SUMPRODUCT($C$6:$L$6,1/(1+$B35)^$C$5:$L$5)+(Assumptions!$C$97*(G$31*Model!$L$31-Assumptions!$C$99)+Assumptions!$C$98*($L$6*(1+Assumptions!$C$6)/($B35-Assumptions!$C$6)))/(1+$B35)^$L$5-Assumptions!$C$8)/Assumptions!$C$7 -> 35.697549
B36: =Assumptions!$C$5+(0.01) -> 0.1169 | C36: =(SUMPRODUCT($C$6:$L$6,1/(1+$B36)^$C$5:$L$5)+(Assumptions!$C$97*(C$31*Model!$L$31-Assumptions!$C$99)+Assumptions!$C$98*($L$6*(1+Assumptions!$C$6)/($B36-Assumptions!$C$6)))/(1+$B36)^$L$5-Assumptions!$C$8)/Assumptions!$C$7 -> 29.162384 | D36: =(SUMPRODUCT($C$6:$L$6,1/(1+$B36)^$C$5:$L$5)+(Assumptions!$C$97*(D$31*Model!$L$31-Assumptions!$C$99)+Assumptions!$C$98*($L$6*(1+Assumptions!$C$6)/($B36-Assumptions!$C$6)))/(1+$B36)^$L$5-Assumptions!$C$8)/Assumptions!$C$7 -> 30.40099 | E36: =(SUMPRODUCT($C$6:$L$6,1/(1+$B36)^$C$5:$L$5)+(Assumptions!$C$97*(E$31*Model!$L$31-Assumptions!$C$99)+Assumptions!$C$98*($L$6*(1+Assumptions!$C$6)/($B36-Assumptions!$C$6)))/(1+$B36)^$L$5-Assumptions!$C$8)/Assumptions!$C$7 -> 31.639597 | F36: =(SUMPRODUCT($C$6:$L$6,1/(1+$B36)^$C$5:$L$5)+(Assumptions!$C$97*(F$31*Model!$L$31-Assumptions!$C$99)+Assumptions!$C$98*($L$6*(1+Assumptions!$C$6)/($B36-Assumptions!$C$6)))/(1+$B36)^$L$5-Assumptions!$C$8)/Assumptions!$C$7 -> 32.878203 | G36: =(SUMPRODUCT($C$6:$L$6,1/(1+$B36)^$C$5:$L$5)+(Assumptions!$C$97*(G$31*Model!$L$31-Assumptions!$C$99)+Assumptions!$C$98*($L$6*(1+Assumptions!$C$6)/($B36-Assumptions!$C$6)))/(1+$B36)^$L$5-Assumptions!$C$8)/Assumptions!$C$7 -> 34.11681
B37: Centre cell (highlighted) = base case; it reconciles to the headline DCF value above. Table is live to all inputs.

Sheet Relative Val
B1: IMAX - Relative Valuation (Trading Multiples)
B2: Blue = input. Applies EV/EBITDA multiples to forward EBITDA. NCI at market, net debt deducted.
B4: SHARED INPUTS
B5: Net debt ($mm) | C5: 132
B6: NCI at market ($mm) | C6: =Assumptions!C8 -> 100
B7: Diluted shares (mm) | C7: =Assumptions!C7 -> 56.6
B8: Current price | C8: =Assumptions!C9 -> 44
B10: EBITDA BASES ($mm) | D10: Note
B11: My 2026E Adj. EBITDA estimate | C11: =Model!C31 -> 233.8936 | D11: Above consensus: 46% margin, box office ~17% above guidance
B12: My 2027E Adj. EBITDA estimate | C12: =Model!D31 -> 221.3142 | D12: Post-peak year (-6%)
B13: Street consensus 2026E EBITDA | C13: 195 | D13: Analyst avg ~$187-200mm. Below my estimate
B15: MULTIPLE REFERENCE POINTS | C15: EV/EBITDA | D15: Source
B16: Traditional exhibitors (AMC, Cinemark) | C16: 6-9x | D16: The bear framing: values IMAX as an exhibitor
B17: Media-Diversified industry median | C17: 7.4x | D17: GuruFocus, Jul-2026
B18: IMAX 10-year median | C18: 14.5x | D18: GuruFocus. The bull anchor
B19: IMAX current forward | C19: ~14x | D19: Street forward EBITDA basis
B20: IMAX current TTM | C20: 19.2x | D20: GuruFocus, Jul-2026 (unadjusted EBITDA)
B21: Asset-light ent. tech / licensing | C21: mid-teens | D21: The bull framing: platform not exhibitor
B23: IMPLIED VALUE PER SHARE | C23: 11 | D23: 12.5 | E23: 14.5
B24: On my 2026E EBITDA | C24: =(C$23*C11-C5-C6)/C7 -> 41.357413 | D24: =(D$23*C11-C5-C6)/C7 -> 47.556007 | E24: =(E$23*C11-C5-C6)/C7 -> 55.820798
B25: On my 2027E EBITDA | C25: =(C$23*C12-C5-C6)/C7 -> 38.912653 | D25: =(D$23*C12-C5-C6)/C7 -> 44.77787 | E25: =(E$23*C12-C5-C6)/C7 -> 52.59816
B26: On street consensus EBITDA | C26: =(C$23*C13-C5-C6)/C7 -> 33.798587 | D26: =(D$23*C13-C5-C6)/C7 -> 38.966431 | E26: =(E$23*C13-C5-C6)/C7 -> 45.85689
B28: Green row = primary case (my 2026E EBITDA of ~$234M). The market ($44) sits between my EBITDA at ~12x and consensus at ~14.5x.
B29: Central trading-comps case used in synthesis: 14.5x on 2026E EBITDA (IMAX 10-yr median).

Sheet Takeover
B1: IMAX - Takeover / M&A Analysis
B2: IMAX confirmed exploring a sale (WSJ, May-2026). A DCF cannot capture a control premium. This layer does.
B4: CONTEXT
B5: - WSJ (21-May-2026): IMAX exploring sale, approached entertainment buyers. "Early stage, may not result in a deal."
B6: - Named buyers: Apple, Amazon, Netflix, Sony, Disney, Comcast, Sphere, private equity.
B7: - Benchmark M&A price target: $60 (raised from $44).
B8: - Precedent: Kinepolis/Emagine ~$105mm (Feb-2026) - but an exhibitor deal, low multiple, weak comp.
B9: - Caution: IMAX ran a sale process in 2006 (Allen & Co / UBS). It FAILED - no buyer met the board price.
B11: METHOD 1: CONTROL PREMIUM ON UNAFFECTED PRICE
B12: Unaffected share price | C12: 38 | D12: Pre-Odyssey / around M&A speculation. NOT the $44 post-run price (avoids double-count).
B13: Premium scenario | C13: Low 25% | D13: Base 35% | E13: High 45%
B14: Premium % | C14: 0.25 | D14: 0.35 | E14: 0.45
B15: Implied takeout price | C15: =C12*(1+C14) -> 47.5 | D15: =C12*(1+D14) -> 51.3 | E15: =C12*(1+E14) -> 55.1
B17: METHOD 2: TAKEOUT MULTIPLE CROSS-CHECK
B18: Applied to 2026E EBITDA ($mm) | C18: =Model!C31 -> 233.8936
B19: Takeout multiple | C19: Low 14x | D19: Base 16x | E19: High 18x
B20: Multiple | C20: 14 | D20: 16 | E20: 18
B21: Implied takeout price | C21: =(C20*C18-132-Assumptions!C8)/Assumptions!C7 -> 53.7546 | D21: =(D20*C18-132-Assumptions!C8)/Assumptions!C7 -> 62.019392 | E21: =(E20*C18-132-Assumptions!C8)/Assumptions!C7 -> 70.284183
B22: Note: Method 2 uses my above-consensus EBITDA, so it runs high. Method 1 (premium on unaffected price) is the cleaner anchor.
B23: Takeover central case used in synthesis: Method 1 base (35% premium).

Sheet Synthesis
B1: IMAX - Valuation Synthesis
B2: Blue = weight input (must sum to 100%). Blended target vs current price.
B4: METHODS | C4: Value/sh | D4: Weight | E4: Contribution
B5: DCF (10-yr, standalone) | C5: =DCF!C21 -> 34.688252 | D5: 0.5 | E5: =C5*D5 -> 17.344126
B6: Trading comps (14.5x 2026E) | C6: ='Relative Val'!E24 -> 55.820798 | D6: 0.5 | E6: =C6*D6 -> 27.910399
B7: Takeover (35% premium, memo) | C7: =Takeover!D15 -> 51.3 | D7: 0 | E7: =C7*D7 -> 0
B8: Weight check (must = 100%) | D8: =SUM(D5:D7) -> 1
B9: BLENDED PRICE TARGET | E9: =SUM(E5:E7) -> 45.254525
B10: Rounded price target | C10: =ROUND(E9,0) -> 45
B11: Current price | C11: =Assumptions!C9 -> 44
B12: Upside / (downside) | C12: =E9/Assumptions!C9-1 -> 0.028511934
B14: PRESET WEIGHTING SCENARIOS
C15: DCF wt | D15: Comps wt | E15: M&A wt (=0) | F15: Target
B16: DCF-heavy (60 / 40) | C16: 0.6 | D16: 0.4 | E16: 0 | F16: =C16*$C$5+D16*$C$6+E16*$C$7 -> 43.14127
B17: Balanced (50 / 50) - base case | C17: 0.5 | D17: 0.5 | E17: 0 | F17: =C17*$C$5+D17*$C$6+E17*$C$7 -> 45.254525
B18: Comps-heavy (40 / 60) | C18: 0.4 | D18: 0.6 | E18: 0 | F18: =C18*$C$5+D18*$C$6+E18*$C$7 -> 47.36778
B21: Takeover is excluded from the blend (0% weight) and shown separately as optionality on the Takeover tab.
B22: Weighting reflects how much to trust cash-flow value vs the market multiple. Base case: 50 / 50.
